djangoldp_webpushnotification/__init__.py
djangoldp_webpushnotification/admin.py
djangoldp_webpushnotification/djangoldp_settings.py
djangoldp_webpushnotification/djangoldp_urls.py
djangoldp_webpushnotification/models.py
djangoldp_webpushnotification/views.py
djangoldp_webpushnotification/migrations/0001_initial.py
djangoldp_webpushnotification/migrations/__init__.py
djangoldp_webpushnotification-1.0.11.dist-info/LICENSE
djangoldp_webpushnotification-1.0.11.dist-info/METADATA
djangoldp_webpushnotification-1.0.11.dist-info/WHEEL
djangoldp_webpushnotification-1.0.11.dist-info/top_level.txt
djangoldp_webpushnotification-1.0.11.dist-info/RECORD
